fastmcp_google_calendar_pro/__init__.py
fastmcp_google_calendar_pro/server.py
fastmcp_google_calendar_pro-0.1.0.dist-info/METADATA
fastmcp_google_calendar_pro-0.1.0.dist-info/WHEEL
fastmcp_google_calendar_pro-0.1.0.dist-info/entry_points.txt
fastmcp_google_calendar_pro-0.1.0.dist-info/RECORD
