Metadata-Version: 2.4
Name: fastmcp-google-calendar-pro
Version: 0.1.0
Summary: Manage Google Calendar events with tools for creating, listing, searching, and checking availability
Requires-Python: >=3.10
Requires-Dist: fastmcp>=2.0.0
